spilot/__init__.py
spilot/app.py
spilot/cli.py
spilot/style.css
spilot-1.0.2.dist-info/licenses/LICENSE
spilot-1.0.2.dist-info/METADATA
spilot-1.0.2.dist-info/WHEEL
spilot-1.0.2.dist-info/entry_points.txt
spilot-1.0.2.dist-info/top_level.txt
spilot-1.0.2.dist-info/RECORD
