Metadata-Version: 2.4
Name: spilot
Version: 1.0.2
Summary: A terminal-based SLURM job monitoring utility that provides a clean, interactive TUI for viewing and managing jobs on HPC clusters.
Home-page: https://github.com/atrey-a/spilot
Author: Saurabh Atreya
Author-email: saurabh@atrey-a.com
Classifier: Programming Language :: Python :: 3
Classifier: License :: OSI Approved :: Apache Software License
Classifier: Operating System :: OS Independent
Requires-Python: >=3.8.1
License-File: LICENSE
Requires-Dist: textual>=2.0.0
Dynamic: author
Dynamic: author-email
Dynamic: classifier
Dynamic: description
Dynamic: description-content-type
Dynamic: home-page
Dynamic: license-file
Dynamic: requires-dist
Dynamic: requires-python
Dynamic: summary
